ka/__init__.py
ka/cli.py
ka/config.py
ka/currency.py
ka/eval.py
ka/functions.py
ka/gui.py
ka/interpret.py
ka/parse.py
ka/plot.py
ka/probability.py
ka/tokens.py
ka/types.py
ka/units.py
ka/utils.py
ka_cli-1.2.0.dist-info/licenses/LICENSE.txt
ka_cli-1.2.0.dist-info/METADATA
ka_cli-1.2.0.dist-info/WHEEL
ka_cli-1.2.0.dist-info/entry_points.txt
ka_cli-1.2.0.dist-info/top_level.txt
ka_cli-1.2.0.dist-info/RECORD
