Metadata-Version: 2.4
Name: ka-cli
Version: 1.2.0
Summary: A calculator language.
Home-page: https://github.com/Kevinpgalligan/ka
Author: Kevin Galligan
Author-email: galligankevinp@gmail.com
Classifier: Programming Language :: Python :: 3
Classifier: License :: OSI Approved :: MIT License
Requires-Python: >=3.6
License-File: LICENSE.txt
Requires-Dist: PyQt5
Requires-Dist: matplotlib
Requires-Dist: pyreadline3
Dynamic: author
Dynamic: author-email
Dynamic: classifier
Dynamic: home-page
Dynamic: license-file
Dynamic: requires-dist
Dynamic: requires-python
Dynamic: summary
